self_signed.py
self_signed-1.0.0.dist-info/METADATA
self_signed-1.0.0.dist-info/WHEEL
self_signed-1.0.0.dist-info/entry_points.txt
self_signed-1.0.0.dist-info/top_level.txt
self_signed-1.0.0.dist-info/RECORD
