Metadata-Version: 2.1
Name: self-signed
Version: 1.0.0
Summary: Create self signed certificates with multiple Domain Names (SANs) with style
Home-page: https://github.com/dwt/self-signed
Author: Martin Häcker, Robert Buchholz
Author-email: spamfaenger@gmx.de
License: BSD 2-Clause License
Platform: UNKNOWN
Classifier: License :: OSI Approved :: BSD License
Classifier: Development Status :: 5 - Production/Stable
Classifier: Environment :: Console
Classifier: Intended Audience :: Developers
Classifier: Intended Audience :: System Administrators
Classifier: Operating System :: POSIX
Classifier: Operating System :: Unix
Classifier: Topic :: Security
Classifier: Topic :: Security :: Cryptography
Classifier: Topic :: Utilities
Classifier: Programming Language :: Python :: 3
Requires-Python: >=3.4
Provides-Extra: test
Requires-Dist: pytest ; extra == 'test'
Requires-Dist: tox ; extra == 'test'
Requires-Dist: twine ; extra == 'test'
Requires-Dist: build ; extra == 'test'
